{
    "source": "Majelis Rasulullah",
    "author": "Imam Abdullah Al-Haddad",
    "name": "قَدْ كَفَانِيْ",
    "latin": "Qod Kafaani",
    "text": {
        "1": {
            "arabic": "ﷲ ﷲ ، ﷲ ﷲ ، ﷲ ﷲ ، ﷲ ﷲ ؛ کﻠﻣﺎﻧﺎدﯾت ﯾﺎھو ﻗﺎل ﯾﺎﻋﺑدي أﻧﺎﷲ",
            "latin": "Allāh Allāh, Allāh Allāh, Allāh Allāh, Allāh Allāh; Kullamā nādaytu Yā Hū, qāla Yā ‘abdī Ana Allāh"
        },
        "2": {
            "arabic": "قَدْ كَفَانِيْ عِلْمُ رَبِّي مِنْ سُؤَالِي وَاخْتِيَارِي",
            "latin": "Qad kafānī ‘ilmu Rabbī min su-ālī wakhtiyārī"
        },
        "3": {
            "arabic": "فَدُعَائِي وَابْتِهَالِي شَاهِدٌ لِي بِافْتِقَارِي",
            "latin": "Fadu’ā-ī wabtihālī syāhidun lī biftiqārī"
        },
        "4": {
            "arabic": "فَلِهَذَا السِّرِّ أَدْعُو فِي يَسَارِي وَعَسَارِي",
            "latin": "Falihādzas-sirri ad’ū fī yasārī wa ‘asārī"
        },
        "5": {
            "arabic": "أَنَا عَبْدٌ صَارَ فَخْرِي ضِمْنَ فَقْرِي وَاضْطِرَارِي",
            "latin": "Ana ‘abdun shāra fakhrī ḍhimna faqrī waḍ-ṭhirārī"
        },
        "6": {
            "arabic": "قَدْ كَفَانِي عِلْمُ رَبِّي مِنْ سُؤَالِي وَاخْتِيَارِي",
            "latin": "Qad kafānī ‘ilmu Rabbī min su-ālī wakhtiyārī"
        },
        "7": {
            "arabic": "يَا إِلَهِي وَمَلِيكِي أَنْتَ تَعْلَمُ كَيْفَ حَالِي",
            "latin": "Yā Ilāhī wa Malīkī, Anta ta’lamu kaifa ḥālī"
        },
        "8": {
            "arabic": "وَبِمَا قَدْ حَلَّ قَلْبِي مِنْ هُمُومٍ وَاشْتِغَالِي",
            "latin": "Wa bimā qad ḥalla qalbī min humūmin wasytighālī"
        },
        "9": {
            "arabic": "فَتَدَارَكْنِي بِلُطْفٍ مِنْكَ يَا مَوْلَى الْمَوَالِي",
            "latin": "Fatadārakni biluṭhfin minka Yā Mawlal-mawālī"
        },
        "10": {
            "arabic": "يَا كَرِيمَ الْوَجْهِ غِثْنِي قَبْلَ أَنْ يَفْنَى اصْطِبَارِي",
            "latin": "Yā Karīmal-Wajhi ghithnī qabla an yafnā-ṣṭibārī"
        },
        "11": {
            "arabic": "قَدْ كَفَانِي عِلْمُ رَبِّي مِنْ سُؤَالِي وَاخْتِيَارِي",
            "latin": "Qad kafānī ‘ilmu Rabbī min su-ālī wakhtiyārī"
        },
        "12": {
            "arabic": "يَا سَرِيعَ الْغَوْثِ غَوْثًا مِنْكَ يُدْرِكْنِي سَرِيعًا",
            "latin": "Yā Sarī’al-ghautsi ghautsan minka yudriknī sarī’ā"
        },
        "13": {
            "arabic": "يُهْزِمُ الْعُسْرَ وَيَأْتِي بِالَّذِي أَرْجُو جَمِيعًا",
            "latin": "Yahzimul-‘usra wa ya-tī billadzī arjū jamī’ā"
        },
        "14": {
            "arabic": "يَا قَرِيبًا يَا مُجِيبًا يَا عَلِيمًا يَا سَمِيعًا",
            "latin": "Yā Qarīban Yā Mujīban Yā ‘Alīman Yā Samī’ā"
        },
        "15": {
            "arabic": "قَدْ تَحَقَّقْتُ بِعَجْزِي وَخُضُوعِي وَانْكِسَارِي",
            "latin": "Qad taḥaqqaqtu bi’ajzī wa khuḍhū’ī wankisārī"
        },
        "16": {
            "arabic": "قَدْ كَفَانِي عِلْمُ رَبِّي مِنْ سُؤَالِي وَاخْتِيَارِي",
            "latin": "Qad kafānī ‘ilmu Rabbī min su-ālī wakhtiyārī"
        },
        "17": {
            "arabic": "لَمْ أَزَلْ بِالْبَابِ وَاقِفْ فَارْحَمَنْ رَبِّي وُقُوفِي",
            "latin": "Lam azal bil-bābi wāqif farḥaman Rabbī wuqūfī"
        },
        "18": {
            "arabic": "وَبِوَادِي الْفَضْلِ عَاكِفْ فَأَدِمْ رَبِّي عُكُوفِي",
            "latin": "Wa biwādil-faḍhli ‘ākif fa-adim Rabbī ‘ukūfī"
        },
        "19": {
            "arabic": "وَلِحُسْنِ الظَّنِّ لَازِمْ فَهُوَ خِلِّي وَحَلِيفِي",
            "latin": "Wa liḥusnizh-zhanni lāzim fahuwa khillī wa ḥalīfī"
        },
        "20": {
            "arabic": "وَأَنِيسِي وَجَلِيسِي طُولَ لَيْلِي وَنَهَارِي",
            "latin": "Wa anīsī wa jalīsī ṭhūla lailī wa nahārī"
        },
        "21": {
            "arabic": "قَدْ كَفَانِي عِلْمُ رَبِّي مِنْ سُؤَالِي وَاخْتِيَارِي",
            "latin": "Qad kafānī ‘ilmu Rabbī min su-ālī wakhtiyārī"
        },
        "22": {
            "arabic": "حَاجَةٌ فِي النَّفْسِ يَا رَبِّ فَاقْضِهَا يَا خَيْرَ قَاضِي",
            "latin": "Ḥājatun fin-nafsi Yā Rabb faqḍihā Yā Khaira Qāḍhī"
        },
        "23": {
            "arabic": "وَأَرِحْ سِرِّي وَقَلْبِي مِنْ لَظَاهَا وَالشُّوَاظِ",
            "latin": "Wa ariḥ sirrī wa qalbī min lazhāhā wasy-syuwāzhi"
        },
        "24": {
            "arabic": "فِي سُرُورٍ وَحُبُورٍ وَإِذَا مَا كُنْتَ رَاضِي",
            "latin": "Fī surūrin wa ḥubūrin wa idzā mā kunta rāḍhī"
        },
        "25": {
            "arabic": "فَالْهَنَا وَالْبَسْطُ حَالِي وَشِعَارِي وَدِثَارِي",
            "latin": "Falhanā wal-basṭhu ḥālī wa syi’ārī wa ditsārī"
        },
        "26": {
            "arabic": "قَدْ كَفَانِي عِلْمُ رَبِّي مِنْ سُؤَالِي وَاخْتِيَارِي",
            "latin": "Qad kafānī ‘ilmu Rabbī min su-ālī wakhtiyārī"
        }
    },
    "translations": {
        "id": {
            "name": "Sungguh Telah Cukup Bagiku",
            "text": {
                "1": "Allah Allah, Allah Allah, Allah Allah, Allah Allah; Setiap kali kumemanggil: wahai Dia (ALLAH), maka Dia menjawab: Wahai Hamba Ku, Akulah Allah.",
                "2": "Sungguh telah cukup bagiku kepuasan dan ketenanganku bahwa Penciptaku Maha Mengetahui Segala Permintaanku dan Usahaku",
                "3": "Maka do’a do’a dan jeritan hatiku sebagai saksiku atas kefakiranku (dihadapan kewibawaanMU)",
                "4": "Maka demi rahasia kefakiranku (dihadapan KewibawaanMu) aku selalau mohon (padaMu) disaat kemudahan dan kesulitanku",
                "5": "Aku adalah hamba yang kebangganku adalah dalamnya kemiskinannku dan besarnya kebutuhanku (padaMu)",
                "6": "Sungguh telah cukup bagiku kepuasan dan ketenanganku bahwa Penciptaku Maha Mengetahui segala permohonan dan usahaku",
                "7": "Wahai Tuhanku Wahai yang memiliki diriku, Engkau Maha Mengetahui bagaimana keadaanku",
                "8": "Dan dari segala yang memenuhi hatiku dari kegundahan dan kesibukanku (hingga terlupakan dari mengingatMu)",
                "9": "Maka ulurkanlah bagiku Kasih Sayang dari Mu Wahai Raja dari segenap para Raja",
                "10": "Wahai Yang Maha Pemurah Dzatnya, tolonglah aku, dengan pertolongan yang datang sebelum sirna kemampuanku dalam bersabar",
                "11": "Sungguh telah cukup bagiku kepuasan dan ketenanganku bahwa penciptaku mengetahui segala permohonan dan usahaku",
                "12": "Wahai Yang Maha cepat mendatangkan pertolongan, temukan kami dengan pertolongan dari Mu yang mendatangi kami dengan segera",
                "13": "Pertolongan yang merubuhkan segala kesulitan, dan mendatangkan segala yang kami harap harapkan",
                "14": "Wahai Yang Maha Dekat, Wahai Yang Maha Menjawab segala rintihan, Wahai Yang Maha Mengetahui, Wahai Yang Maha Mendengar",
                "15": "Sungguh aku telah benar-benar meyakini kelemahan dan ketidakmampuanku, kerendahan dan keluluhanku",
                "16": "Sungguh telah cukup bagiku kepuasan dan ketenanganku bahwa penciptaku Maha Mengetahui segala Permohonan dan usahaku",
                "17": "Aku masih tetap berdiri di Gerbang Mu, maka kasihanilah aku yang masih terus menunggu",
                "18": "Dan di Lembah Anugerah Kasih SayangMu aku berdiam maka abadikanlah keadaanku ini",
                "19": "Maka bersangka baik padaMu adalah hal yang mesti bagiku, sangka baik atasMu adalah pakaianku dan janjiku",
                "20": "Dan hal itulah (sangka baik padaMu) yang menjadi penenang hatiku, dan selalu (sangka baik pada Mu) menemaniku sepanjang malamku dan siangku",
                "21": "Sungguh telah cukup bagiku kepuasan dan ketenanganku bahwa penciptaku Maha Mengetahui Segala permohonan dan usahaku",
                "22": "Segala kebutuhan dalam diriku Wahai Penciptaku maka selesaikanlah, Wahai sebaik-baik yang menyelesaikan kebutuhan",
                "23": "Dan tenangkanlah ruhku dan sanubariku dari gejolak dan gemuruhnya (nafsu, kemarahan, kesedihan, dan kebingungan)",
                "24": "Agar hatiku dan ruhku selalu dalam ketentraman dan kedamaian dalam apa-apa yang telah engkau Ridhoi",
                "25": "Maka kegembiraan dan kebahagiaan menjadi keadaanku selalu, dan menjadi lambang kehidupanku dan selubung perhiasanku",
                "26": "Sungguh telah cukup bagiku kepuasan dan ketenangan bahwa penciptaku Maha Mengetahui Segala permohonan dan usahaku."
            }
        }
    },
    "last_updated": "2025-11-17"
}